photonic/__init__.py
photonic/_logging/__init__.py
photonic/_logging/configs/__init__.py
photonic/_logging/formatters/__init__.py
photonic/_logging/formatters/color_formatter.py
photonic/_logging/handlers/__init__.py
photonic/_logging/handlers/console_handler.py
photonic/_logging/handlers/json_file_handler.py
photonic/_logging/loggers/__init__.py
photonic/_logging/loggers/logger.py
photonic/enums/__init__.py
photonic/enums/colors/__init__.py
photonic/utils/__init__.py
photonic/utils/threading_utils/__init__.py
photonic/utils/time_utils/__init__.py
photonic-0.0.1.dist-info/METADATA
photonic-0.0.1.dist-info/WHEEL
photonic-0.0.1.dist-info/licenses/LICENSE
photonic-0.0.1.dist-info/RECORD
