Metadata-Version: 2.1
Name: photonic
Version: 0.0.1
Summary: My neat tools grouped together!
Project-URL: Homepage, https://github.com/Asem1090/photonic
Project-URL: Bug Tracker, https://github.com/Asem1090/photonic/issues
Author-email: Asem Shouman <asem.sh2004@gmail.com>
License-File: LICENSE
Classifier: License :: OSI Approved :: Apache Software License
Classifier: Operating System :: OS Independent
Classifier: Programming Language :: Python :: 3
Requires-Python: >=3.6
